hyper/__init__.py
hyper/certs.pem
hyper/cli.py
hyper/compat.py
hyper/contrib.py
hyper/httplib_compat.py
hyper/ssl_compat.py
hyper/tls.py
hyper/common/__init__.py
hyper/common/bufsocket.py
hyper/common/connection.py
hyper/common/decoder.py
hyper/common/exceptions.py
hyper/common/headers.py
hyper/common/util.py
hyper/http11/__init__.py
hyper/http11/connection.py
hyper/http11/parser.py
hyper/http11/response.py
hyper/http20/__init__.py
hyper/http20/connection.py
hyper/http20/errors.py
hyper/http20/exceptions.py
hyper/http20/response.py
hyper/http20/stream.py
hyper/http20/util.py
hyper/http20/window.py
hyper/packages/__init__.py
hyper/packages/hpack/__init__.py
hyper/packages/hpack/compat.py
hyper/packages/hpack/exceptions.py
hyper/packages/hpack/hpack.py
hyper/packages/hpack/hpack_compat.py
hyper/packages/hpack/huffman.py
hyper/packages/hpack/huffman_constants.py
hyper/packages/hyperframe/__init__.py
hyper/packages/hyperframe/flags.py
hyper/packages/hyperframe/frame.py
hyper/packages/rfc3986/LICENSE
hyper/packages/rfc3986/__init__.py
hyper/packages/rfc3986/api.py
hyper/packages/rfc3986/compat.py
hyper/packages/rfc3986/exceptions.py
hyper/packages/rfc3986/misc.py
hyper/packages/rfc3986/normalizers.py
hyper/packages/rfc3986/parseresult.py
hyper/packages/rfc3986/uri.py
hyper-0.6.2.dist-info/DESCRIPTION.rst
hyper-0.6.2.dist-info/METADATA
hyper-0.6.2.dist-info/RECORD
hyper-0.6.2.dist-info/WHEEL
hyper-0.6.2.dist-info/entry_points.txt
hyper-0.6.2.dist-info/metadata.json
hyper-0.6.2.dist-info/top_level.txt
